epub_generator/__init__.py
epub_generator/context.py
epub_generator/data/container.xml.jinja
epub_generator/data/content.opf.jinja
epub_generator/data/cover.xhtml.jinja
epub_generator/data/mimetype.jinja
epub_generator/data/nav.xhtml.jinja
epub_generator/data/part.xhtml.jinja
epub_generator/data/style.css.jinja
epub_generator/generation/__init__.py
epub_generator/generation/gen_asset.py
epub_generator/generation/gen_chapter.py
epub_generator/generation/gen_content.py
epub_generator/generation/gen_epub.py
epub_generator/generation/gen_nav.py
epub_generator/generation/gen_toc.py
epub_generator/generation/xml_utils.py
epub_generator/html_tag.py
epub_generator/i18n.py
epub_generator/options.py
epub_generator/template.py
epub_generator/types.py
epub_generator/validate.py
epub_generator-0.1.6.dist-info/LICENSE
epub_generator-0.1.6.dist-info/METADATA
epub_generator-0.1.6.dist-info/WHEEL
epub_generator-0.1.6.dist-info/RECORD
