Metadata-Version: 2.3
Name: epub-generator
Version: 0.1.6
Summary: A simple Python EPUB 3.0 generator with a single API call
License: MIT
Keywords: epub,epub3,ebook,generator,publishing
Author: Tao Zeyu
Author-email: i@taozeyu.com
Requires-Python: >=3.10,<3.14
Classifier: Development Status :: 4 - Beta
Classifier: Intended Audience :: Developers
Classifier: License :: OSI Approved :: MIT License
Classifier: Programming Language :: Python :: 3
Classifier: Programming Language :: Python :: 3.10
Classifier: Programming Language :: Python :: 3.11
Classifier: Programming Language :: Python :: 3.12
Classifier: Programming Language :: Python :: 3.13
Classifier: Topic :: Software Development :: Libraries :: Python Modules
Classifier: Topic :: Text Processing :: Markup :: HTML
Classifier: Topic :: Text Processing :: Markup :: XML
Requires-Dist: jinja2 (>=3.1.5,<4.0.0)
Requires-Dist: latex2mathml (>=3.77.0,<4.0.0)
Requires-Dist: matplotlib (>=3.10.1,<3.11.0)
Project-URL: Homepage, https://github.com/moskize91/epub-generator
Project-URL: Repository, https://github.com/moskize91/epub-generator
